cyal/util.pxd
cyal/listener.cpython-312-darwin.so
cyal/capture.pxd
cyal/source.pxd
cyal/al.pxd
cyal/efx.pyx
cyal/exceptions.pxd
cyal/buffer.cpython-312-darwin.so
cyal/efx.cpython-312-darwin.so
cyal/listener.pyx
cyal/context.pxd
cyal/efx_api.pxd
cyal/buffer.pxd
cyal/alc.pxd
cyal/__init__.py
cyal/context.cpython-312-darwin.so
cyal/capture.cpython-312-darwin.so
cyal/about.py
cyal/hrtf.pyx
cyal/util.cpython-312-darwin.so
cyal/hrtf.cpython-312-darwin.so
cyal/device.pxd
cyal/device.pyx
cyal/hrtf.pxd
cyal/libopenal.dylib
cyal/buffer.pyx
cyal/source.cpython-312-darwin.so
cyal/context.pyx
cyal/listener.pxd
cyal/exceptions.pyx
cyal/libopenal.1.23.1.dylib
cyal/libopenal.1.dylib
cyal/efx.pxd
cyal/exceptions.cpython-312-darwin.so
cyal/device.cpython-312-darwin.so
cyal/capture.pyx
cyal/source.pyx
cyal/util.pyx
cyal-0.4.5.dist-info/RECORD
cyal-0.4.5.dist-info/WHEEL
cyal-0.4.5.dist-info/METADATA
cyal-0.4.5.dist-info/licenses/LICENSE
