Metadata-Version: 2.2
Name: cyal
Version: 0.4.5
Summary: Cython bindings for OpenAL
Keywords: audio,openal,cython,bindings
Author-Email: Michael Connor Buchan <mikey@blindcomputing.org>
License: MIT License
Classifier: Development Status :: 4 - Beta
Classifier: Programming Language :: Cython
Classifier: Programming Language :: Python
Classifier: Programming Language :: Python :: 3
Classifier: License :: OSI Approved :: MIT License
Classifier: Operating System :: OS Independent
Classifier: Intended Audience :: Developers
Classifier: Topic :: Multimedia
Classifier: Topic :: Multimedia :: Sound/Audio
Classifier: Topic :: Multimedia :: Sound/Audio :: Capture/Recording
Classifier: Topic :: Multimedia :: Sound/Audio :: Players
Project-URL: Homepage, https://github.com/lower-elements/cyal#readme
Project-URL: Repository, https://github.com/lower-elements/cyal
Project-URL: Bug Tracker, https://github.com/lower-elements/cyal/issues
Project-URL: Contribute, https://github.com/lower-elements/cyal/pull/new
Requires-Python: >=3.10
